Metadata-Version: 2.1
Name: skillshare
Version: 0.1.0
Summary: Async library to download Skillshare Courses
Home-page: https://gitlab.com/TECHNOFAB/skillshare
Author: Technofab
Author-email: skillshare.git@technofab.de
License: MIT
Platform: UNKNOWN
Requires-Python: >=3.5
